{
  "timestamp": "2025-07-10T00:40:13.380272",
  "analysis_id": 274,
  "timestep": 274000,
  "elapsed_time": 11558.455481052399,
  "algorithm": "dapg",
  "metrics": {
    "episode_reward": {
      "mean": -145.4,
      "std": 20.434284915308393,
      "min": -150.0,
      "max": -40.0,
      "count": 100
    },
    "episode_length": {
      "mean": 145.45,
      "std": 20.220472299132876,
      "min": 41,
      "max": 150
    },
    "success_rate": {
      "rate": 0.05,
      "count": 100
    },
    "policy_loss": {
      "mean": -0.0045216698199510574,
      "std": 0.0,
      "trend": "stable"
    },
    "value_loss": {
      "mean": 2.3814666271209717,
      "std": 0.0,
      "trend": "stable"
    },
    "bc_loss": {
      "mean": -4.672889220460472,
      "std": 8.881784197001252e-16,
      "trend": "stable"
    }
  },
  "health_check": {
    "status": "healthy",
    "issues": []
  },
  "recommendations": [
    {
      "type": "bc_weight",
      "action": "decrease",
      "reason": "BC loss low but poor performance - reduce BC weight",
      "priority": "high"
    }
  ],
  "warnings": []
}