{
  "timestamp": "2025-07-10T02:46:27.141963",
  "analysis_id": 456,
  "timestep": 456000,
  "elapsed_time": 19132.217171669006,
  "algorithm": "dapg",
  "metrics": {
    "episode_reward": {
      "mean": -145.66,
      "std": 19.058446946170612,
      "min": -150.0,
      "max": -48.0,
      "count": 100
    },
    "episode_length": {
      "mean": 145.72,
      "std": 18.84467033407589,
      "min": 49,
      "max": 150
    },
    "success_rate": {
      "rate": 0.06,
      "count": 100
    },
    "policy_loss": {
      "mean": 0.07687661051750183,
      "std": 0.0,
      "trend": "stable"
    },
    "value_loss": {
      "mean": 10.236246109008789,
      "std": 0.0,
      "trend": "stable"
    },
    "bc_loss": {
      "mean": -4.761952442991481,
      "std": 8.881784197001252e-16,
      "trend": "stable"
    }
  },
  "health_check": {
    "status": "needs_attention",
    "issues": [
      {
        "type": "high_value_loss",
        "severity": "warning",
        "message": "Value function loss is high - may need more training data"
      }
    ]
  },
  "recommendations": [
    {
      "type": "bc_weight",
      "action": "decrease",
      "reason": "BC loss low but poor performance - reduce BC weight",
      "priority": "high"
    }
  ],
  "warnings": []
}